tigrex/__init__.py
tigrex/__main__.py
tigrex-1.3.0.dist-info/LICENSE
tigrex-1.3.0.dist-info/METADATA
tigrex-1.3.0.dist-info/WHEEL
tigrex-1.3.0.dist-info/entry_points.txt
tigrex-1.3.0.dist-info/top_level.txt
tigrex-1.3.0.dist-info/RECORD
