Metadata-Version: 2.1
Name: tigrex
Version: 1.3.0
Summary: A Magic the Gathering CLI Tool
Home-page: https://github.com/ericjaychi/tigrex
Author: Eric Chi
Author-email: ericjaychi@gmail.com
License: UNKNOWN
Platform: UNKNOWN
Classifier: Programming Language :: Python :: 3.7
Classifier: License :: OSI Approved :: MIT License
Classifier: Operating System :: OS Independent
Requires-Dist: requests (<=2.21.0)
Requires-Dist: fire (<=0.1.3)
